idem_aws_auto
